spislv/SPI_SLAVE.v
module SPI_SLAVE(
input wire 		SPI_CLK,
input wire 		SPI_RST,
input wire 		SPI_CS,
input wire 	[2:0]	SID_assign, 		//hard wired
input wire 		SPI_MOSI,
output reg 		SPI_MISO
);

//states
localparam [2:0] IDLE = 3'd0;
localparam [2:0] ADDR = 3'd1;
localparam [2:0] WRITE = 3'd2;
localparam [2:0] READ = 3'd3;
localparam [2:0] EOF = 3'd4;
localparam [2:0] CONF = 3'd5;

reg [3:0] CS;
reg [2:0] SID_r;
reg wr_r;
reg SID_FAIL;
reg [6:0] addr_r;
reg [5:0] ctrl_cnt;
reg [31:0] din_r;
reg [31:0] dout_r;
reg [31:0] slave_register [0:127];

//reg MISO;
wire SID_match;
wire reset_n;
wire [31:0] reg_data_ch;
assign  SID_match = (SID_assign==SID_r);
assign  reset_n = SPI_RST & (!SPI_CS);  
assign	reg_data_ch = slave_register [addr_r];
//bit wise AND : &
//1-bit true false : &&
//! 1-bit , ~ bit wise inverting

//state transition                               
always@(negedge SPI_CLK or negedge reset_n)
begin
		if(!reset_n)
			CS <= IDLE;

		else if((CS == IDLE) && SID_match && (ctrl_cnt == 6'd3) && !SID_FAIL)  //IDLE_END
			CS <= ADDR;

		else if((CS == IDLE) && !SID_match && (ctrl_cnt == 6'd3) && !SID_FAIL) //SID not match
			CS <= IDLE;

		else if((CS == ADDR) && (ctrl_cnt == 6'd6) && (wr_r) && !SID_FAIL) //ADDR_END 
			CS <= WRITE;

		else if((CS == ADDR) && (ctrl_cnt == 6'd6) && (!wr_r) && !SID_FAIL) // READ_START
			CS <= READ;

		else if((CS == WRITE) && (ctrl_cnt == 6'd31) && !SID_FAIL) //WRITE_END
			CS <= EOF;

		else if((CS == READ) && (ctrl_cnt == 6'd31) && !SID_FAIL) // RETRUN to EOF
			CS <= EOF;

		else if(CS == EOF) // CONFIRM for one cycle 
			CS <= CONF;

		else if(CS == CONF) //RETURN TO IDLE
			CS <= IDLE;

		else 
			CS <= CS;
end

//control counter 
always@(negedge SPI_CLK or negedge reset_n)
begin
	if(!reset_n)
		ctrl_cnt <= 6'd0;

	else if((CS == IDLE) && SID_match && (ctrl_cnt == 6'd3))
		ctrl_cnt <= 6'd0;

	else if((CS == IDLE) && !SID_match && (ctrl_cnt == 6'd3))
		ctrl_cnt <= 6'd0;

	else if((CS == ADDR) && (ctrl_cnt == 6'd6) && (wr_r))
		ctrl_cnt <= 6'd0;

	else if((CS == ADDR) && (ctrl_cnt == 6'd6) && (!wr_r))
		ctrl_cnt <= 6'd0;

	else if((CS == WRITE) && (ctrl_cnt == 6'd31)) 
		ctrl_cnt <= 6'd0;

	else if((CS == READ) && (ctrl_cnt == 6'd32))
		ctrl_cnt <= 6'd0;

	else if(CS == EOF) 
		ctrl_cnt <= 6'd0;
	
	else if(CS == CONF)
		ctrl_cnt <= 6'd0;

	else if(SID_FAIL)
		ctrl_cnt <= 6'd0;

	else 
		ctrl_cnt <= ctrl_cnt + 6'd1;
end

//MOSI -> SID_r
always@(negedge SPI_CLK or negedge reset_n)
begin
		if(!reset_n)
			SID_r <= 3'b0;

		else if(CS == IDLE)
			SID_r[2-ctrl_cnt] <= SPI_MOSI;

		else if((CS == IDLE) && !SID_match && (ctrl_cnt == 6'd3)) //SID not match
			SID_r <= 3'd0;

end

//IF SID DID NOT MATCHED ASSERTING FAIL FLAG SIGNAL
always@(negedge SPI_CLK or negedge reset_n)
begin
	if(!reset_n)
		SID_FAIL <= 1'b0;

	else if((CS == IDLE) && !SID_match && (ctrl_cnt == 3'd3))
		SID_FAIL <= 1'b1;
end

//MOSI -> wr_r
always@(negedge SPI_CLK or negedge reset_n)
begin
		if(!reset_n)
			wr_r <= 1'b0;

		else if((CS == IDLE) && (ctrl_cnt == 6'd3))
			wr_r <= SPI_MOSI;

end

//MOSI -> addr_r 
always@(negedge SPI_CLK or negedge reset_n)
begin
		if(!reset_n)
			addr_r <= 7'd0;
					
		else if(CS == ADDR)
			addr_r[6-ctrl_cnt] <= SPI_MOSI;
 
end

//MOSI -> din_r
always@(negedge SPI_CLK or negedge reset_n)
begin
		if(!reset_n)
			din_r <= 32'd0;

		else if(CS == WRITE)
			din_r[31-ctrl_cnt] <= SPI_MOSI;
end

//dout_r
always@(negedge SPI_CLK or negedge reset_n)
begin
	if(!reset_n)
		dout_r <= 32'b0;

	else if((CS == ADDR) && (ctrl_cnt == 6'd6) && (!wr_r))
		dout_r <= slave_register [addr_r];
end

//at read state 
always@(posedge SPI_CLK or negedge reset_n)
begin
	if(!reset_n)
		SPI_MISO <= 1'b0;

	else if((CS == READ))
	begin
		dout_r <= dout_r << 1'b1;
		SPI_MISO <= dout_r[31]; 
	end
end 
// at EOF (End Of signal) state
always@(negedge SPI_CLK)
begin
	if(!SPI_CS && (CS == EOF) && wr_r)

		slave_register [addr_r] <= din_r ;
	
end



endmodule

spislv/tb_spi.v
//`timescale 1ns/10ps
`define TCLK    250

module tb_spi;  

wire            SPI_SOMI;
wire    [5:0]   ctrlCNT;
//wire	[2:0]	state;

//wire 	[31:0]	written_data;
//wire	[2:0]	SID_ch;
//wire	[6:0]	addr_ch;
//wire	[31:0]	din_ch;
//wire		wr_r_ch;
//wire	[31:0]	dout;
reg             write_on;
reg             Reset_n;

reg             SPI_CS;
reg             SCK;
reg             SPI_SIMO;
reg             SPI_CLK;

reg     [31:0]  received_data;

reg     [42:0]  shift_wdata;
reg     [10:0]  shift_rdata;


// Hardwired ID of DUT
localparam  [2:0]   SPI_ID_VALUE = 3'b010;


SPI_SLAVE  DUT (
    	
    // Hardwired ID
    .SID_assign         (SPI_ID_VALUE),

    // Active Low Asynchronous Global Reset
    .SPI_RST           (Reset_n),

    // 4-Wire Signals for SPI
    .SPI_CS             (SPI_CS),
    .SPI_CLK            (SPI_CLK),
    .SPI_MOSI           (SPI_SIMO),
    .SPI_MISO           (SPI_SOMI)//,
//    .CST		(state),
//    .reg_val		(written_data),
//    .SID_ch		(SID_ch),
//    .addr_ch		(addr_ch),
//    .din_ch		(din_ch),
//    .wr_r_ch		(wr_r_ch),
//    .cnt		(ctrlCNT),
//    .dout		(dout)
);


// clk generators
initial 
begin
  SCK = 1'b0;
end

always #(`TCLK/2.0) SCK <= ~SCK;

// Reset
initial
begin
    		   Reset_n <= 1'b1;
    #(`TCLK*1)     Reset_n <= 1'b0;
    #(`TCLK*10)    Reset_n <= 1'b1;
end

// Simulation End
initial
begin
    $dumpfile("SPI_SLAVE.vcd");
    $dumpvars();
    #(`TCLK*400);
    $finish; 
end

// write (CS(1bit,Active LOW), SID(3bit), WRB(1bit) == 1'b1, ADDRESS(7bit), DATA(32bit));
// read (CS(1bit,Active LOW), SID(3bit), WRB(1bit) == 1'b0, ADDRESS(7bit));
// cmp (ADDRESS(7bit), expectedData(8bit));
initial 
begin
      SPI_CS = 1'b1;
      #(`TCLK*12);
      #(`TCLK/2);
      write(1'b0, SPI_ID_VALUE, 1'b1, 7'd30, 32'h92345679);
      done(1'b1);
    
      #(`TCLK*12);

      read(1'b0, 3'b111, 1'b0, 7'd30);
      cmp(7'd30,32'h92345679);
      done(1'b1);
      read(1'b0, SPI_ID_VALUE, 1'b0, 7'd30);
      cmp(7'd30,32'h92345679);
      done(1'b1);

  //  $dumpfile("SPI_SLAVE.vcd");
  //  $dumpvars();
    #(`TCLK*20);
end


always @* 
begin
    if(SPI_CS == 1'b0) 
        SPI_CLK <= SCK;
      
    else 
        SPI_CLK <= 1'b0;
end


task write;
   input CS;
   input [2:0] SID;
   input wrb;
   input [6:0] addr;
   input [31:0] data;

   begin
      SPI_CS = CS;
      write_on = 1'b1;
      shift_wdata = {SID,wrb,addr,data};
      $write("WRITE : At[%2d] = 0x%0x\n", addr,data);
      #(`TCLK*44);
   end

endtask


task read;
   input CS;
   input [2:0] SID;
   input wrb;
   input [6:0] addr;

   begin
      SPI_CS = CS;
      write_on = 1'b0;
      shift_rdata = {SID,wrb,addr};
      #(`TCLK*44);
   end

endtask

task cmp;
   input [6:0] addr;
   input [31:0] expectedData;

    begin
        if(expectedData != received_data) 
        begin
            $write("****** READ ERROR : At[%2d] = Expected 0x%0x, got 0x%0x\n", addr,expectedData, received_data);
        end

        else 
        begin
            $write("READ : At[%2d] = 0x%0x\n", addr,received_data);
        end
   end

endtask


task done;
   input CS;

   begin
      SPI_CS = CS;
      #(`TCLK);
   end

endtask

always @(posedge SPI_CLK or negedge Reset_n) 
begin
    if (~Reset_n) 
    begin
        SPI_SIMO <= 1'b0;
        shift_wdata <= 43'h0;
        shift_rdata <= 11'h000;
    end
    
    // For Write
    else if(write_on == 1'b1)
    begin
        shift_wdata <= shift_wdata << 1'b1;
        SPI_SIMO <= shift_wdata[42];
    end

    // For Read
    else if(write_on == 1'b0)
    begin
        shift_rdata <= shift_rdata << 1'b1;
        SPI_SIMO <= shift_rdata[10];
    end
end

// For Read


   always @(negedge SPI_CLK or negedge Reset_n)
   begin
      if (~Reset_n) 
      begin
         received_data <= 32'h0;
      end

      else if(write_on == 1'b0 && DUT.ctrl_cnt >= 5'd0 && DUT.ctrl_cnt <= 5'd31)
      begin
         received_data <= {received_data[30:0],SPI_SOMI};
      end
   end



endmodule

spislv/SPI_SLAVE.vcd
$date
	Tue Jun 09 12:38:01 2015
$end
$version
	ModelSim Version 10.1d
$end
$timescale
	1ps
$end
$scope module tb_spi $end
$var parameter 3 ! SPI_ID_VALUE $end
$var wire 1 " SPI_SOMI $end
$var wire 1 # ctrlCNT [5] $end
$var wire 1 $ ctrlCNT [4] $end
$var wire 1 % ctrlCNT [3] $end
$var wire 1 & ctrlCNT [2] $end
$var wire 1 ' ctrlCNT [1] $end
$var wire 1 ( ctrlCNT [0] $end
$var reg 1 ) write_on $end
$var reg 1 * Reset_n $end
$var reg 1 + SPI_CS $end
$var reg 1 , SCK $end
$var reg 1 - SPI_SIMO $end
$var reg 1 . SPI_CLK $end
$var reg 32 / received_data [31:0] $end
$var reg 43 0 shift_wdata [42:0] $end
$var reg 11 1 shift_rdata [10:0] $end
$scope task write $end
$var reg 1 2 CS $end
$var reg 3 3 SID [2:0] $end
$var reg 1 4 wrb $end
$var reg 7 5 addr [6:0] $end
$var reg 32 6 data [31:0] $end
$upscope $end
$scope task read $end
$var reg 1 7 CS $end
$var reg 3 8 SID [2:0] $end
$var reg 1 9 wrb $end
$var reg 7 : addr [6:0] $end
$upscope $end
$scope task cmp $end
$var reg 7 ; addr [6:0] $end
$var reg 32 < expectedData [31:0] $end
$upscope $end
$scope task done $end
$var reg 1 = CS $end
$upscope $end
$scope module DUT $end
$var parameter 3 > IDLE $end
$var parameter 3 ? ADDR $end
$var parameter 3 @ WRITE $end
$var parameter 3 A READ $end
$var parameter 3 B EOF $end
$var parameter 3 C CONF $end
$var wire 1 D SPI_CLK $end
$var wire 1 E SPI_RST $end
$var wire 1 F SPI_CS $end
$var wire 1 G SID_assign [2] $end
$var wire 1 H SID_assign [1] $end
$var wire 1 I SID_assign [0] $end
$var wire 1 J SPI_MOSI $end
$var reg 1 K SPI_MISO $end
$var reg 4 L CS [3:0] $end
$var reg 3 M SID_r [2:0] $end
$var reg 1 N wr_r $end
$var reg 1 O SID_FAIL $end
$var reg 7 P addr_r [6:0] $end
$var reg 6 Q ctrl_cnt [5:0] $end
$var reg 32 R din_r [31:0] $end
$var reg 32 S dout_r [31:0] $end
$var wire 1 T SID_match $end
$var wire 1 U reset_n $end
$var wire 1 V reg_data_ch [31] $end
$var wire 1 W reg_data_ch [30] $end
$var wire 1 X reg_data_ch [29] $end
$var wire 1 Y reg_data_ch [28] $end
$var wire 1 Z reg_data_ch [27] $end
$var wire 1 [ reg_data_ch [26] $end
$var wire 1 \ reg_data_ch [25] $end
$var wire 1 ] reg_data_ch [24] $end
$var wire 1 ^ reg_data_ch [23] $end
$var wire 1 _ reg_data_ch [22] $end
$var wire 1 ` reg_data_ch [21] $end
$var wire 1 a reg_data_ch [20] $end
$var wire 1 b reg_data_ch [19] $end
$var wire 1 c reg_data_ch [18] $end
$var wire 1 d reg_data_ch [17] $end
$var wire 1 e reg_data_ch [16] $end
$var wire 1 f reg_data_ch [15] $end
$var wire 1 g reg_data_ch [14] $end
$var wire 1 h reg_data_ch [13] $end
$var wire 1 i reg_data_ch [12] $end
$var wire 1 j reg_data_ch [11] $end
$var wire 1 k reg_data_ch [10] $end
$var wire 1 l reg_data_ch [9] $end
$var wire 1 m reg_data_ch [8] $end
$var wire 1 n reg_data_ch [7] $end
$var wire 1 o reg_data_ch [6] $end
$var wire 1 p reg_data_ch [5] $end
$var wire 1 q reg_data_ch [4] $end
$var wire 1 r reg_data_ch [3] $end
$var wire 1 s reg_data_ch [2] $end
$var wire 1 t reg_data_ch [1] $end
$var wire 1 u reg_data_ch [0] $end
$upscope $end
$upscope $end
$enddefinitions $end
#0
$dumpvars
x)
1*
1+
0,
x-
0.
bx /
bx 0
bx 1
0K
b0 L
b0 M
0N
0O
b0 P
b0 Q
b0 R
b0 S
x2
bx 3
x4
bx 5
bx 6
x7
bx 8
x9
bx :
bx ;
bx <
x=
b10 !
b0 >
b1 ?
b10 @
b11 A
b100 B
b101 C
0"
z(
z'
z&
z%
z$
z#
0T
0U
xu
xt
xs
xr
xq
xp
xo
xn
xm
xl
xk
xj
xi
xh
xg
xf
xe
xd
xc
xb
xa
x`
x_
x^
x]
x\
x[
xZ
xY
xX
xW
xV
xJ
0D
1F
1E
0I
1H
0G
$end
#125
1,
#250
0*
0,
0E
0-
b0 0
b0 1
b0 /
0J
#375
1,
#500
0,
#625
1,
#750
0,
#875
1,
#1000
0,
#1125
1,
#1250
0,
#1375
1,
#1500
0,
#1625
1,
#1750
0,
#1875
1,
#2000
0,
#2125
1,
#2250
0,
#2375
1,
#2500
0,
#2625
1,
#2750
1*
0,
1E
#2875
1,
#3000
0,
#3125
02
b10 3
14
b11110 5
b10010010001101000101011001111001 6
0+
1)
b101001111010010010001101000101011001111001 0
0F
1U
1,
1.
1D
b1010011110100100100011010001010110011110010 0
#3250
0,
0.
0D
b1 Q
#3375
1,
1.
1D
b100111101001001000110100010101100111100100 0
1-
1J
#3500
0,
0.
0D
b10 Q
b10 M
1T
#3625
1,
1.
1D
b1001111010010010001101000101011001111001000 0
0-
0J
#3750
0,
0.
0D
b11 Q
#3875
1,
1.
1D
b11110100100100011010001010110011110010000 0
1-
1J
#4000
0,
0.
0D
b1 L
b0 Q
1N
#4125
1,
1.
1D
b111101001001000110100010101100111100100000 0
0-
0J
#4250
0,
0.
0D
b1 Q
#4375
1,
1.
1D
b1111010010010001101000101011001111001000000 0
#4500
0,
0.
0D
b10 Q
#4625
1,
1.
1D
b1110100100100011010001010110011110010000000 0
1-
1J
#4750
0,
0.
0D
b11 Q
b10000 P
#4875
1,
1.
1D
b1101001001000110100010101100111100100000000 0
#5000
0,
0.
0D
b100 Q
b11000 P
#5125
1,
1.
1D
b1010010010001101000101011001111001000000000 0
#5250
0,
0.
0D
b101 Q
b11100 P
#5375
1,
1.
1D
b100100100011010001010110011110010000000000 0
#5500
0,
0.
0D
b110 Q
b11110 P
#5625
1,
1.
1D
b1001001000110100010101100111100100000000000 0
0-
0J
#5750
0,
0.
0D
b10 L
b0 Q
#5875
1,
1.
1D
b10010001101000101011001111001000000000000 0
1-
1J
#6000
0,
0.
0D
b1 Q
b10000000000000000000000000000000 R
#6125
1,
1.
1D
b100100011010001010110011110010000000000000 0
0-
0J
#6250
0,
0.
0D
b10 Q
#6375
1,
1.
1D
b1001000110100010101100111100100000000000000 0
#6500
0,
0.
0D
b11 Q
#6625
1,
1.
1D
b10001101000101011001111001000000000000000 0
1-
1J
#6750
0,
0.
0D
b100 Q
b10010000000000000000000000000000 R
#6875
1,
1.
1D
b100011010001010110011110010000000000000000 0
0-
0J
#7000
0,
0.
0D
b101 Q
#7125
1,
1.
1D
b1000110100010101100111100100000000000000000 0
#7250
0,
0.
0D
b110 Q
#7375
1,
1.
1D
b1101000101011001111001000000000000000000 0
1-
1J
#7500
0,
0.
0D
b111 Q
b10010010000000000000000000000000 R
#7625
1,
1.
1D
b11010001010110011110010000000000000000000 0
0-
0J
#7750
0,
0.
0D
b1000 Q
#7875
1,
1.
1D
b110100010101100111100100000000000000000000 0
#8000
0,
0.
0D
b1001 Q
#8125
1,
1.
1D
b1101000101011001111001000000000000000000000 0
#8250
0,
0.
0D
b1010 Q
#8375
1,
1.
1D
b1010001010110011110010000000000000000000000 0
1-
1J
#8500
0,
0.
0D
b1011 Q
b10010010001000000000000000000000 R
#8625
1,
1.
1D
b100010101100111100100000000000000000000000 0
#8750
0,
0.
0D
b1100 Q
b10010010001100000000000000000000 R
#8875
1,
1.
1D
b1000101011001111001000000000000000000000000 0
0-
0J
#9000
0,
0.
0D
b1101 Q
#9125
1,
1.
1D
b1010110011110010000000000000000000000000 0
1-
1J
#9250
0,
0.
0D
b1110 Q
b10010010001101000000000000000000 R
#9375
1,
1.
1D
b10101100111100100000000000000000000000000 0
0-
0J
#9500
0,
0.
0D
b1111 Q
#9625
1,
1.
1D
b101011001111001000000000000000000000000000 0
#9750
0,
0.
0D
b10000 Q
#9875
1,
1.
1D
b1010110011110010000000000000000000000000000 0
#10000
0,
0.
0D
b10001 Q
#10125
1,
1.
1D
b101100111100100000000000000000000000000000 0
1-
1J
#10250
0,
0.
0D
b10010 Q
b10010010001101000100000000000000 R
#10375
1,
1.
1D
b1011001111001000000000000000000000000000000 0
0-
0J
#10500
0,
0.
0D
b10011 Q
#10625
1,
1.
1D
b110011110010000000000000000000000000000000 0
1-
1J
#10750
0,
0.
0D
b10100 Q
b10010010001101000101000000000000 R
#10875
1,
1.
1D
b1100111100100000000000000000000000000000000 0
0-
0J
#11000
0,
0.
0D
b10101 Q
#11125
1,
1.
1D
b1001111001000000000000000000000000000000000 0
1-
1J
#11250
0,
0.
0D
b10110 Q
b10010010001101000101010000000000 R
#11375
1,
1.
1D
b11110010000000000000000000000000000000000 0
#11500
0,
0.
0D
b10111 Q
b10010010001101000101011000000000 R
#11625
1,
1.
1D
b111100100000000000000000000000000000000000 0
0-
0J
#11750
0,
0.
0D
b11000 Q
#11875
1,
1.
1D
b1111001000000000000000000000000000000000000 0
#12000
0,
0.
0D
b11001 Q
#12125
1,
1.
1D
b1110010000000000000000000000000000000000000 0
1-
1J
#12250
0,
0.
0D
b11010 Q
b10010010001101000101011001000000 R
#12375
1,
1.
1D
b1100100000000000000000000000000000000000000 0
#12500
0,
0.
0D
b11011 Q
b10010010001101000101011001100000 R
#12625
1,
1.
1D
b1001000000000000000000000000000000000000000 0
#12750
0,
0.
0D
b11100 Q
b10010010001101000101011001110000 R
#12875
1,
1.
1D
b10000000000000000000000000000000000000000 0
#13000
0,
0.
0D
b11101 Q
b10010010001101000101011001111000 R
#13125
1,
1.
1D
b100000000000000000000000000000000000000000 0
0-
0J
#13250
0,
0.
0D
b11110 Q
#13375
1,
1.
1D
b1000000000000000000000000000000000000000000 0
#13500
0,
0.
0D
b11111 Q
#13625
1,
1.
1D
b0 0
1-
1J
#13750
0,
0.
0D
b100 L
b0 Q
b10010010001101000101011001111001 R
#13875
1,
1.
1D
0-
0J
#14000
0,
0.
0D
b101 L
1u
0t
0s
1r
1q
1p
1o
0n
0m
1l
1k
0j
1i
0h
1g
0f
0e
0d
1c
0b
1a
1`
0_
0^
0]
1\
0[
0Z
1Y
0X
0W
1V
#14125
1=
1+
1F
0U
1,
b0 L
b0 M
0N
b0 P
b0 R
0T
xu
xt
xs
xr
xq
xp
xo
xn
xm
xl
xk
xj
xi
xh
xg
xf
xe
xd
xc
xb
xa
x`
x_
x^
x]
x\
x[
xZ
xY
xX
xW
xV
#14250
0,
#14375
1,
#14500
0,
#14625
1,
#14750
0,
#14875
1,
#15000
0,
#15125
1,
#15250
0,
#15375
1,
#15500
0,
#15625
1,
#15750
0,
#15875
1,
#16000
0,
#16125
1,
#16250
0,
#16375
1,
#16500
0,
#16625
1,
#16750
0,
#16875
1,
#17000
0,
#17125
1,
#17250
0,
#17375
07
b111 8
09
b11110 :
0+
0)
b11100011110 1
0F
1U
1,
1.
1D
b11000111100 1
1-
1J
#17500
0,
0.
0D
b1 Q
b100 M
#17625
1,
1.
1D
b10001111000 1
#17750
0,
0.
0D
b10 Q
b110 M
#17875
1,
1.
1D
b11110000 1
#18000
0,
0.
0D
b11 Q
b111 M
#18125
1,
1.
1D
b111100000 1
0-
0J
#18250
0,
0.
0D
b0 Q
1O
#18375
1,
1.
1D
b1111000000 1
#18500
0,
0.
0D
b11 M
#18625
1,
1.
1D
b11110000000 1
#18750
0,
0.
0D
#18875
1,
1.
1D
b11100000000 1
1-
1J
#19000
0,
0.
0D
b111 M
#19125
1,
1.
1D
b11000000000 1
#19250
0,
0.
0D
#19375
1,
1.
1D
b10000000000 1
#19500
0,
0.
0D
#19625
1,
1.
1D
b0 1
#19750
0,
0.
0D
#19875
1,
1.
1D
0-
0J
#20000
0,
0.
0D
b11 M
#20125
1,
1.
1D
#20250
0,
0.
0D
#20375
1,
1.
1D
#20500
0,
0.
0D
#20625
1,
1.
1D
#20750
0,
0.
0D
#20875
1,
1.
1D
#21000
0,
0.
0D
#21125
1,
1.
1D
#21250
0,
0.
0D
#21375
1,
1.
1D
#21500
0,
0.
0D
#21625
1,
1.
1D
#21750
0,
0.
0D
#21875
1,
1.
1D
#22000
0,
0.
0D
#22125
1,
1.
1D
#22250
0,
0.
0D
#22375
1,
1.
1D
#22500
0,
0.
0D
#22625
1,
1.
1D
#22750
0,
0.
0D
#22875
1,
1.
1D
#23000
0,
0.
0D
#23125
1,
1.
1D
#23250
0,
0.
0D
#23375
1,
1.
1D
#23500
0,
0.
0D
#23625
1,
1.
1D
#23750
0,
0.
0D
#23875
1,
1.
1D
#24000
0,
0.
0D
#24125
1,
1.
1D
#24250
0,
0.
0D
#24375
1,
1.
1D
#24500
0,
0.
0D
#24625
1,
1.
1D
#24750
0,
0.
0D
#24875
1,
1.
1D
#25000
0,
0.
0D
#25125
1,
1.
1D
#25250
0,
0.
0D
#25375
1,
1.
1D
#25500
0,
0.
0D
#25625
1,
1.
1D
#25750
0,
0.
0D
#25875
1,
1.
1D
#26000
0,
0.
0D
#26125
1,
1.
1D
#26250
0,
0.
0D
#26375
1,
1.
1D
#26500
0,
0.
0D
#26625
1,
1.
1D
#26750
0,
0.
0D
#26875
1,
1.
1D
#27000
0,
0.
0D
#27125
1,
1.
1D
#27250
0,
0.
0D
#27375
1,
1.
1D
#27500
0,
0.
0D
#27625
1,
1.
1D
#27750
0,
0.
0D
#27875
1,
1.
1D
#28000
0,
0.
0D
#28125
1,
1.
1D
#28250
0,
0.
0D
#28375
b11110 ;
b10010010001101000101011001111001 <
1+
1F
0U
1,
b0 M
0O
#28500
0,
#28625
b10 8
0+
b1000011110 1
0F
1U
1,
1.
1D
b10000111100 1
#28750
0,
0.
0D
b1 Q
#28875
1,
1.
1D
b1111000 1
1-
1J
#29000
0,
0.
0D
b10 Q
b10 M
1T
#29125
1,
1.
1D
b11110000 1
0-
0J
#29250
0,
0.
0D
b11 Q
#29375
1,
1.
1D
b111100000 1
#29500
0,
0.
0D
b1 L
b0 Q
#29625
1,
1.
1D
b1111000000 1
#29750
0,
0.
0D
b1 Q
#29875
1,
1.
1D
b11110000000 1
#30000
0,
0.
0D
b10 Q
#30125
1,
1.
1D
b11100000000 1
1-
1J
#30250
0,
0.
0D
b11 Q
b10000 P
#30375
1,
1.
1D
b11000000000 1
#30500
0,
0.
0D
b100 Q
b11000 P
#30625
1,
1.
1D
b10000000000 1
#30750
0,
0.
0D
b101 Q
b11100 P
#30875
1,
1.
1D
b0 1
#31000
0,
0.
0D
b110 Q
b11110 P
1u
0t
0s
1r
1q
1p
1o
0n
0m
1l
1k
0j
1i
0h
1g
0f
0e
0d
1c
0b
1a
1`
0_
0^
0]
1\
0[
0Z
1Y
0X
0W
1V
#31125
1,
1.
1D
0-
0J
#31250
0,
0.
0D
b11 L
b0 Q
b10010010001101000101011001111001 S
#31375
1,
1.
1D
b100100011010001010110011110010 S
1K
1"
#31500
0,
0.
0D
b1 Q
b1 /
#31625
1,
1.
1D
b1001000110100010101100111100100 S
0K
0"
#31750
0,
0.
0D
b10 Q
b10 /
#31875
1,
1.
1D
b10010001101000101011001111001000 S
#32000
0,
0.
0D
b11 Q
b100 /
#32125
1,
1.
1D
b100011010001010110011110010000 S
1K
1"
#32250
0,
0.
0D
b100 Q
b1001 /
#32375
1,
1.
1D
b1000110100010101100111100100000 S
0K
0"
#32500
0,
0.
0D
b101 Q
b10010 /
#32625
1,
1.
1D
b10001101000101011001111001000000 S
#32750
0,
0.
0D
b110 Q
b100100 /
#32875
1,
1.
1D
b11010001010110011110010000000 S
1K
1"
#33000
0,
0.
0D
b111 Q
b1001001 /
#33125
1,
1.
1D
b110100010101100111100100000000 S
0K
0"
#33250
0,
0.
0D
b1000 Q
b10010010 /
#33375
1,
1.
1D
b1101000101011001111001000000000 S
#33500
0,
0.
0D
b1001 Q
b100100100 /
#33625
1,
1.
1D
b11010001010110011110010000000000 S
#33750
0,
0.
0D
b1010 Q
b1001001000 /
#33875
1,
1.
1D
b10100010101100111100100000000000 S
1K
1"
#34000
0,
0.
0D
b1011 Q
b10010010001 /
#34125
1,
1.
1D
b1000101011001111001000000000000 S
#34250
0,
0.
0D
b1100 Q
b100100100011 /
#34375
1,
1.
1D
b10001010110011110010000000000000 S
0K
0"
#34500
0,
0.
0D
b1101 Q
b1001001000110 /
#34625
1,
1.
1D
b10101100111100100000000000000 S
1K
1"
#34750
0,
0.
0D
b1110 Q
b10010010001101 /
#34875
1,
1.
1D
b101011001111001000000000000000 S
0K
0"
#35000
0,
0.
0D
b1111 Q
b100100100011010 /
#35125
1,
1.
1D
b1010110011110010000000000000000 S
#35250
0,
0.
0D
b10000 Q
b1001001000110100 /
#35375
1,
1.
1D
b10101100111100100000000000000000 S
#35500
0,
0.
0D
b10001 Q
b10010010001101000 /
#35625
1,
1.
1D
b1011001111001000000000000000000 S
1K
1"
#35750
0,
0.
0D
b10010 Q
b100100100011010001 /
#35875
1,
1.
1D
b10110011110010000000000000000000 S
0K
0"
#36000
0,
0.
0D
b10011 Q
b1001001000110100010 /
#36125
1,
1.
1D
b1100111100100000000000000000000 S
1K
1"
#36250
0,
0.
0D
b10100 Q
b10010010001101000101 /
#36375
1,
1.
1D
b11001111001000000000000000000000 S
0K
0"
#36500
0,
0.
0D
b10101 Q
b100100100011010001010 /
#36625
1,
1.
1D
b10011110010000000000000000000000 S
1K
1"
#36750
0,
0.
0D
b10110 Q
b1001001000110100010101 /
#36875
1,
1.
1D
b111100100000000000000000000000 S
#37000
0,
0.
0D
b10111 Q
b10010010001101000101011 /
#37125
1,
1.
1D
b1111001000000000000000000000000 S
0K
0"
#37250
0,
0.
0D
b11000 Q
b100100100011010001010110 /
#37375
1,
1.
1D
b11110010000000000000000000000000 S
#37500
0,
0.
0D
b11001 Q
b1001001000110100010101100 /
#37625
1,
1.
1D
b11100100000000000000000000000000 S
1K
1"
#37750
0,
0.
0D
b11010 Q
b10010010001101000101011001 /
#37875
1,
1.
1D
b11001000000000000000000000000000 S
#38000
0,
0.
0D
b11011 Q
b100100100011010001010110011 /
#38125
1,
1.
1D
b10010000000000000000000000000000 S
#38250
0,
0.
0D
b11100 Q
b1001001000110100010101100111 /
#38375
1,
1.
1D
b100000000000000000000000000000 S
#38500
0,
0.
0D
b11101 Q
b10010010001101000101011001111 /
#38625
1,
1.
1D
b1000000000000000000000000000000 S
0K
0"
#38750
0,
0.
0D
b11110 Q
b100100100011010001010110011110 /
#38875
1,
1.
1D
b10000000000000000000000000000000 S
#39000
0,
0.
0D
b11111 Q
b1001001000110100010101100111100 /
#39125
1,
1.
1D
b0 S
1K
1"
#39250
0,
0.
0D
b100 L
b100000 Q
b10010010001101000101011001111001 /
#39375
1,
1.
1D
#39500
0,
0.
0D
b101 L
b0 Q
#39625
1+
1F
0U
1,
b0 L
b0 M
b0 P
0K
0T
xu
xt
xs
xr
xq
xp
xo
xn
xm
xl
xk
xj
xi
xh
xg
xf
xe
xd
xc
xb
xa
x`
x_
x^
x]
x\
x[
xZ
xY
xX
xW
xV
0"
#39750
0,
#39875
1,
#40000
0,
#40125
1,
#40250
0,
#40375
1,
#40500
0,
#40625
1,
#40750
0,
#40875
1,
#41000
0,
#41125
1,
#41250
0,
#41375
1,
#41500
0,
#41625
1,
#41750
0,
#41875
1,
#42000
0,
#42125
1,
#42250
0,
#42375
1,
#42500
0,
#42625
1,
#42750
0,
#42875
1,
#43000
0,
#43125
1,
#43250
0,
#43375
1,
#43500
0,
#43625
1,
#43750
0,
#43875
1,
#44000
0,
#44125
1,
#44250
0,
#44375
1,
#44500
0,
#44625
1,
#44750
0,
#44875
1,
#45000
0,
#45125
1,
#45250
0,
#45375
1,
#45500
0,
#45625
1,
#45750
0,
#45875
1,
#46000
0,
#46125
1,
#46250
0,
#46375
1,
#46500
0,
#46625
1,
#46750
0,
#46875
1,
#47000
0,
#47125
1,
#47250
0,
#47375
1,
#47500
0,
#47625
1,
#47750
0,
#47875
1,
#48000
0,
#48125
1,
#48250
0,
#48375
1,
#48500
0,
#48625
1,
#48750
0,
#48875
1,
#49000
0,
#49125
1,
#49250
0,
#49375
1,
#49500
0,
#49625
1,
#49750
0,
#49875
1,
#50000
0,
#50125
1,
#50250
0,
#50375
1,
#50500
0,
#50625
1,
#50750
0,
#50875
1,
#51000
0,
#51125
1,
#51250
0,
#51375
1,
#51500
0,
#51625
1,
#51750
0,
#51875
1,
#52000
0,
#52125
1,
#52250
0,
#52375
1,
#52500
0,
#52625
1,
#52750
0,
#52875
1,
#53000
0,
#53125
1,
#53250
0,
